StatMechGlass/__init__.py
StatMechGlass/stat_mech_glass.py
StatMechGlass/Data/AlB/Cs.csv
StatMechGlass/Data/AlB/Li.csv
StatMechGlass/Data/AlB/Na.csv
StatMechGlass/Data/AlSi/Ca.csv
StatMechGlass/Data/B2O3/Cs.csv
StatMechGlass/Data/B2O3/K.csv
StatMechGlass/Data/B2O3/Li.csv
StatMechGlass/Data/B2O3/Na.csv
StatMechGlass/Data/P2O5/Cs.csv
StatMechGlass/Data/P2O5/Li.csv
StatMechGlass/Data/P2O5/Mg.csv
StatMechGlass/Data/P2O5/Na.csv
StatMechGlass/Data/P2O5/Zn.csv
StatMechGlass/Data/SiB/Na.csv
StatMechGlass/Data/SiO2/Cs.csv
StatMechGlass/Data/SiO2/K.csv
StatMechGlass/Data/SiO2/Na.csv
StatMechGlass/Data/SiO2/Na_Tg.csv
StatMechGlass/Parameters/Al2O3/Al.csv
StatMechGlass/Parameters/Al2O3/AlB.csv
StatMechGlass/Parameters/Al2O3/Ca.csv
StatMechGlass/Parameters/Al2O3/Na.csv
StatMechGlass/Parameters/B2O3/Al.csv
StatMechGlass/Parameters/B2O3/K.csv
StatMechGlass/Parameters/B2O3/Na.csv
StatMechGlass/Parameters/MF/AlSi.csv
StatMechGlass/Parameters/MF/BAl.csv
StatMechGlass/Parameters/MF/BSi.csv
StatMechGlass/Parameters/MF/SiAl.csv
StatMechGlass/Parameters/MF/SiB.csv
StatMechGlass/Parameters/P2O5/Na.csv
StatMechGlass/Parameters/SiO2/Al.csv
StatMechGlass/Parameters/SiO2/Ca.csv
StatMechGlass/Parameters/SiO2/K.csv
StatMechGlass/Parameters/SiO2/Na.csv
StatMechGlass/stat_mech_module/__init__.py
StatMechGlass/stat_mech_module/stat_mech_aluminoborate.py
StatMechGlass/stat_mech_module/stat_mech_borate.py
StatMechGlass/stat_mech_module/stat_mech_phosphate.py
StatMechGlass/stat_mech_module/stat_mech_silicate.py
StatMechGlass-0.1.5.dist-info/LICENCE
StatMechGlass-0.1.5.dist-info/METADATA
StatMechGlass-0.1.5.dist-info/WHEEL
StatMechGlass-0.1.5.dist-info/top_level.txt
StatMechGlass-0.1.5.dist-info/RECORD
