Metadata-Version: 2.1
Name: StatMechGlass
Version: 0.1.5
Summary: Calculates structure of oxide glasses using statistical mechanics
Home-page: https://github.com/OxideGlassGroupAAU/StatMechGlass
Author: Mikkel Bødker
Author-email: mikkelboedker@gmail.com
License: UNKNOWN
Keywords: glass,statistical mechanics
Platform: UNKNOWN
Classifier: Programming Language :: Python :: 3.6
Classifier: Programming Language :: Python :: 3.7
Classifier: Programming Language :: Python :: 3.8
Classifier: License :: OSI Approved :: GNU General Public License v3 or later (GPLv3+)
Classifier: Operating System :: OS Independent
Classifier: Development Status :: 2 - Pre-Alpha
Classifier: Topic :: Scientific/Engineering
Classifier: Intended Audience :: Science/Research
Classifier: Environment :: Console
Requires-Python: >=3.6
License-File: LICENCE
Requires-Dist: numpy (>=1.16)
Requires-Dist: scipy (>=1.2)
Requires-Dist: matplotlib (>=3.4.2)
Requires-Dist: sklearn
